endid/__init__.py
endid/cmd.py
endid/endid.py
endid-0.0.8.dist-info/LICENSE
endid-0.0.8.dist-info/METADATA
endid-0.0.8.dist-info/WHEEL
endid-0.0.8.dist-info/entry_points.txt
endid-0.0.8.dist-info/top_level.txt
endid-0.0.8.dist-info/RECORD
