Metadata-Version: 2.1
Name: endid
Version: 0.0.8
Summary: Command line utility to call the Endid.app Slack app
Home-page: https://github.com/endid-app/endid-python
Author: Dan Lester
Author-email: support@endid.app
License: UNKNOWN
Platform: UNKNOWN
Classifier: Programming Language :: Python :: 3
Classifier: License :: OSI Approved :: MIT License
Classifier: Operating System :: OS Independent
Requires-Python: >=2.7
License-File: LICENSE
